algorithms/__init__.py
algorithms/epsilon_greedy/__init__.py
algorithms/epsilon_greedy/annealing.py
algorithms/epsilon_greedy/standard.py
algorithms/epsilon_greedy/test_annealing.py
algorithms/epsilon_greedy/test_standard.py
algorithms/exp3/__init__.py
algorithms/exp3/exp3.py
algorithms/exp3/test_exp3.py
algorithms/hedge/__init__.py
algorithms/hedge/hedge.py
algorithms/hedge/test_hedge.py
algorithms/softmax/__init__.py
algorithms/softmax/annealing.py
algorithms/softmax/standard.py
algorithms/softmax/test_annealing.py
algorithms/softmax/test_standard.py
algorithms/ucb/__init__.py
algorithms/ucb/test_ucb1.py
algorithms/ucb/test_ucb2.py
algorithms/ucb/ucb1.py
algorithms/ucb/ucb2.py
arms/__init__.py
arms/adversarial.py
arms/bernoulli.py
arms/normal.py
testing_framework/__init__.py
testing_framework/tests.py
banditsbook-0.1.1.dist-info/LICENSE.md
banditsbook-0.1.1.dist-info/METADATA
banditsbook-0.1.1.dist-info/WHEEL
banditsbook-0.1.1.dist-info/top_level.txt
banditsbook-0.1.1.dist-info/RECORD
