Metadata-Version: 2.1
Name: banditsbook
Version: 0.1.1
Summary: Python code from the book Bandit Algorithms for Website Optimization
Home-page: https://gitlab.com/winderresearch/rl/BanditsBook/
Author: Phil Winder
Author-email: phil@WinderResearch.com
License: UNKNOWN
Project-URL: Bug Reports, https://gitlab.com/winderresearch/rl/BanditsBook/issues
Project-URL: Source, https://gitlab.com/winderresearch/rl/BanditsBook/
Keywords: rl bandits abtesting
Platform: UNKNOWN
Classifier: Development Status :: 3 - Alpha
Classifier: Intended Audience :: Developers
Classifier: Topic :: Software Development :: Libraries :: Python Modules
Classifier: License :: OSI Approved :: MIT License
Classifier: Programming Language :: Python :: 3.6
Classifier: Programming Language :: Python :: 3.7
Requires-Python: >=3.5
